gajou/__init__.py
gajou/db_helper.py
gajou/singleton.py
gajou/cli/__init__.py
gajou/cli/base_cli.py
gajou/cli/cli_response.py
gajou/cli/return_codes.py
gajou/grpc/__init__.py
gajou/grpc/base_interceptor.py
gajou/grpc/base_stub.py
gajou/grpc/grpc_error.py
gajou/http/__init__.py
gajou/http/base_http.py
gajou/http/errors/__init__.py
gajou/http/errors/access_error.py
gajou/http/errors/auth_error.py
gajou/http/errors/bad_request_error.py
gajou/http/errors/base_http_error.py
gajou/http/errors/not_found_error.py
gajou/http/errors/server_error.py
gajou/http/errors/unprocessable_entity_error.py
gajou-0.3.3.dist-info/LICENSE
gajou-0.3.3.dist-info/METADATA
gajou-0.3.3.dist-info/WHEEL
gajou-0.3.3.dist-info/top_level.txt
gajou-0.3.3.dist-info/RECORD
