Metadata-Version: 2.1
Name: gajou
Version: 0.3.3
Summary: Base classes and helpers to make QA autotests for API and CLI
Home-page: https://github.com/ArtyomKomarenko/kaa
Author: Artyom Komarenko
Author-email: artyom.komarenko@mail.ru
License: MIT License
Platform: UNKNOWN
Classifier: Programming Language :: Python :: 3
Classifier: License :: OSI Approved :: MIT License
Classifier: Operating System :: OS Independent
Requires-Python: >=3.7
License-File: LICENSE
Requires-Dist: grpcio
Requires-Dist: psycopg2-binary
Requires-Dist: requests
